{"1":{"name":"Ethereum Mainnet","explorer":"https://etherscan.io","api":"https://api.etherscan.io/api"},"3":{"name":"Ropsten","explorer":"https://ropsten.etherscan.io","api":""},"4":{"name":"Rinkeby","explorer":"https://rinkeby.etherscan.io","api":""},"5":{"name":"Goerli","explorer":"https://goerli.etherscan.io","api":"https://api-goerli.etherscan.io/api"},"7":{"name":"ThaiChain","explorer":"https://exp.thaichain.org","api":""},"8":{"name":"Ubiq","explorer":"https://ubiqscan.io","api":""},"10":{"name":"OP Mainnet","explorer":"https://optimistic.etherscan.io","api":"https://api-optimistic.etherscan.io/api"},"14":{"name":"Flare Mainnet","explorer":"https://flare-explorer.flare.network","api":""},"16":{"name":"Flare Testnet Coston","explorer":"https://coston-explorer.flare.network","api":""},"18":{"name":"ThunderCore Testnet","explorer":"https://explorer-testnet.thundercore.com","api":""},"19":{"name":"Songbird Canary-Network","explorer":"https://songbird-explorer.flare.network","api":""},"20":{"name":"Elastos Smart Chain","explorer":"https://esc.elastos.io","api":""},"21":{"name":"Elastos Smart Chain Testnet","explorer":"https://esc-testnet.elastos.io","api":""},"30":{"name":"Rootstock Mainnet","explorer":"https://explorer.rsk.co","api":""},"31":{"name":"Rootstock Testnet","explorer":"https://explorer.testnet.rsk.co","api":""},"34":{"name":"SecureChain Mainnet","explorer":"https://explorer.securechain.ai","api":""},"36":{"name":"Dxchain Mainnet","explorer":"https://dxscan.io","api":""},"37":{"name":"Xpla Mainnet","explorer":"https://explorer.xpla.io/mainnet","api":""},"39":{"name":"U2U Solaris Mainnet","explorer":"https://u2uscan.xyz","api":""},"40":{"name":"Telos EVM Mainnet","explorer":"https://teloscan.io","api":""},"41":{"name":"Telos EVM Testnet","explorer":"https://testnet.teloscan.io","api":""},"42":{"name":"LUKSO Mainnet","explorer":"https://explorer.execution.mainnet.lukso.network","api":""},"47":{"name":"Acria IntelliChain","explorer":"https://explorer.acria.ai","api":""},"48":{"name":"Ennothem Mainnet Proterozoic","explorer":"https://etmscan.network","api":""},"49":{"name":"Ennothem Testnet Pioneer","explorer":"https://pioneer.etmscan.network","api":""},"50":{"name":"XDC Network","explorer":"https://xdcscan.io","api":""},"51":{"name":"XDC Apothem Network","explorer":"https://apothem.xinfinscan.com","api":""},"56":{"name":"BNB Smart Chain Mainnet","explorer":"https://bscscan.com","api":"https://api.bscscan.com/api"},"57":{"name":"Syscoin Mainnet","explorer":"https://explorer.syscoin.org","api":""},"58":{"name":"Ontology Mainnet","explorer":"https://explorer.ont.io","api":""},"60":{"name":"GoChain","explorer":"https://explorer.gochain.io","api":""},"61":{"name":"Ethereum Classic Mainnet","explorer":"https://blockscout.com/etc/mainnet","api":""},"63":{"name":"Ethereum Classic Testnet Mordor","explorer":"https://blockscout.com/etc/mordor","api":""},"65":{"name":"OKExChain Testnet","explorer":"https://www.oklink.com/okexchain-test","api":""},"66":{"name":"OKXChain Mainnet","explorer":"https://www.oklink.com/en/okc","api":""},"69":{"name":"Optimism Kovan","explorer":"https://kovan-optimistic.etherscan.io","api":""},"70":{"name":"Hoo Smart Chain","explorer":"https://www.hooscan.com","api":""},"73":{"name":"FNCY","explorer":"https://fncyscan.fncy.world","api":""},"74":{"name":"IDChain Mainnet","explorer":"https://explorer.idchain.one","api":""},"75":{"name":"Decimal Smart Chain Mainnet","explorer":"https://explorer.decimalchain.com","api":""},"77":{"name":"POA Network Sokol","explorer":"https://blockscout.com/poa/sokol","api":""},"79":{"name":"Zenith Mainnet","explorer":"https://scan.zenithchain.co","api":""},"80":{"name":"GeneChain","explorer":"https://scan.genechain.io","api":""},"81":{"name":"Japan Open Chain Mainnet","explorer":"https://explorer.japanopenchain.org","api":""},"82":{"name":"Meter Mainnet","explorer":"https://scan.meter.io","api":""},"83":{"name":"Meter Testnet","explorer":"https://scan-warringstakes.meter.io","api":""},"84":{"name":"Linqto Devnet","explorer":"https://explorer.linqto-dev.com","api":""},"85":{"name":"GateChain Testnet","explorer":"https://www.gatescan.org/testnet","api":""},"86":{"name":"GateChain Mainnet","explorer":"https://www.gatescan.org","api":""},"87":{"name":"Nova Network","explorer":"https://explorer.novanetwork.io","api":""},"90":{"name":"Garizon Stage0","explorer":"https://explorer.garizon.com","api":""},"91":{"name":"Garizon Stage1","explorer":"https://explorer.garizon.com","api":""},"92":{"name":"Garizon Stage2","explorer":"https://explorer.garizon.com","api":""},"93":{"name":"Garizon Stage3","explorer":"https://explorer.garizon.com","api":""},"94":{"name":"SwissDLT","explorer":"https://explorer.swissdlt.ch","api":""},"95":{"name":"CamDL Mainnet","explorer":"https://explorer.camdl.gov.kh","api":""},"97":{"name":"BNB Smart Chain Testnet","explorer":"https://testnet.bscscan.com","api":"https://api-testnet.bscscan.com/api"},"99":{"name":"POA Network Core","explorer":"https://blockscout.com/poa/core","api":""},"100":{"name":"Gnosis","explorer":"https://gnosisscan.io","api":""},"103":{"name":"Worldland Mainnet","explorer":"https://scan.worldland.foundation","api":""},"104":{"name":"Kaiba Lightning Chain Testnet","explorer":"https://kaibascan.io","api":""},"106":{"name":"Velas EVM Mainnet","explorer":"https://evmexplorer.velas.com","api":""},"107":{"name":"Nebula Testnet","explorer":"https://explorer.novanetwork.io","api":""},"108":{"name":"ThunderCore Mainnet","explorer":"https://viewblock.io/thundercore","api":""},"112":{"name":"Coinbit Mainnet","explorer":"https://coinbit-explorer.chain.sbcrypto.app","api":""},"113":{"name":"Dehvo","explorer":"https://explorer.dehvo.com","api":""},"114":{"name":"Flare Testnet Coston2","explorer":"https://coston2-explorer.flare.network","api":""},"119":{"name":"ENULS Mainnet","explorer":"https://evmscan.nuls.io","api":""},"120":{"name":"ENULS Testnet","explorer":"https://beta.evmscan.nuls.io","api":""},"121":{"name":"Realchain Mainnet","explorer":"https://rclscan.com","api":""},"122":{"name":"Fuse Mainnet","explorer":"https://explorer.fuse.io","api":""},"128":{"name":"Huobi ECO Chain Mainnet","explorer":"https://hecoinfo.com","api":""},"134":{"name":"iExec Sidechain","explorer":"https://blockscout.bellecour.iex.ec","api":""},"135":{"name":"Alyx Chain Testnet","explorer":"https://testnet.alyxscan.com","api":""},"136":{"name":"Deamchain Mainnet","explorer":"https://scan.deamchain.com","api":""},"137":{"name":"Polygon Mainnet","explorer":"https://polygonscan.com","api":""},"139":{"name":"WoopChain Mainnet","explorer":"https://explorer.wikiwoop.com","api":""},"148":{"name":"ShimmerEVM Mainnet","explorer":"https://explorer.evm.shimmer.network","api":""},"155":{"name":"Tenet Testnet","explorer":"https://testnet.tenetscan.io","api":""},"156":{"name":"OEBlock Testnet","explorer":"https://testnet.oescan.io","api":""},"161":{"name":"Armonia Eva Chain Testnet","explorer":"https://testnet.evascan.io","api":""},"165":{"name":"Omni Testnet","explorer":"https://testnet.explorer.omni.network","api":""},"167":{"name":"Atoshi Testnet","explorer":"https://scan.atoverse.info","api":""},"168":{"name":"AIOZ Network","explorer":"https://explorer.aioz.network","api":""},"169":{"name":"Manta Pacific Mainnet","explorer":"https://pacific-explorer.manta.network","api":""},"180":{"name":"AME Chain Mainnet","explorer":"https://amescan.io","api":""},"193":{"name":"Crypto Emergency","explorer":"https://cemscan.com","api":""},"195":{"name":"X1 Testnet","explorer":"https://www.oklink.com/x1-test","api":""},"197":{"name":"Neutrinos TestNet","explorer":"https://testnet.neutrinoschain.com","api":""},"198":{"name":"Bitchain Mainnet","explorer":"https://explorer.bitchain.biz","api":""},"199":{"name":"BitTorrent Chain Mainnet","explorer":"https://bttcscan.com","api":""},"200":{"name":"Arbitrum on xDai","explorer":"https://blockscout.com/xdai/arbitrum","api":""},"204":{"name":"opBNB Mainnet","explorer":"https://mainnet.opbnbscan.com","api":""},"210":{"name":"Bitnet","explorer":"https://btnscan.com","api":""},"212":{"name":"MAP Makalu","explorer":"https://testnet.mapscan.io","api":""},"214":{"name":"Shinarium Mainnet","explorer":"https://shinascan.shinarium.org","api":""},"225":{"name":"LACHAIN Mainnet","explorer":"https://scan.lachain.io","api":""},"226":{"name":"LACHAIN Testnet","explorer":"https://scan-test.lachain.io","api":""},"236":{"name":"Deamchain Testnet","explorer":"https://testnet-scan.deamchain.com","api":""},"242":{"name":"Plinga Mainnet","explorer":"https://www.plgscan.com","api":""},"248":{"name":"Oasys Mainnet","explorer":"https://explorer.oasys.games","api":""},"250":{"name":"Fantom Opera","explorer":"https://ftmscan.com","api":""},"255":{"name":"Kroma","explorer":"https://blockscout.kroma.network","api":""},"259":{"name":"Neonlink Mainnet","explorer":"https://scan.neonlink.io","api":""},"262":{"name":"SUR Blockchain Network","explorer":"https://explorer.surnet.org","api":""},"269":{"name":"High Performance Blockchain","explorer":"https://hscan.org","api":""},"271":{"name":"EgonCoin Mainnet","explorer":"https://egonscan.com","api":""},"274":{"name":"LaChain","explorer":"https://explorer.lachain.network","api":""},"280":{"name":"zkSync Era Testnet","explorer":"https://goerli.explorer.zksync.io","api":""},"291":{"name":"Orderly Mainnet","explorer":"https://explorer.orderly.network","api":""},"303":{"name":"Neurochain Testnet","explorer":"https://testnet.ncnscan.com","api":""},"309":{"name":"Wyzth Testnet","explorer":"http://24.199.108.65:4000","api":""},"311":{"name":"Omax Mainnet","explorer":"https://omaxray.com","api":""},"313":{"name":"Neurochain Mainnet","explorer":"https://ncnscan.com","api":""},"321":{"name":"KCC Mainnet","explorer":"https://explorer.kcc.io/en","api":""},"322":{"name":"KCC Testnet","explorer":"https://scan-testnet.kcc.network","api":""},"324":{"name":"zkSync Era Mainnet","explorer":"https://explorer.zksync.io","api":""},"333":{"name":"Web3Q Mainnet","explorer":"https://explorer.mainnet.web3q.io","api":""},"345":{"name":"Yooldo Verse Mainnet","explorer":"https://explorer.yooldo-verse.xyz","api":""},"361":{"name":"Theta Mainnet","explorer":"https://explorer.thetatoken.org","api":""},"363":{"name":"Theta Sapphire Testnet","explorer":"https://guardian-testnet-sapphire-explorer.thetatoken.org","api":""},"364":{"name":"Theta Amber Testnet","explorer":"https://guardian-testnet-amber-explorer.thetatoken.org","api":""},"365":{"name":"Theta Testnet","explorer":"https://testnet-explorer.thetatoken.org","api":""},"369":{"name":"PulseChain","explorer":"https://scan.pulsechain.com","api":""},"371":{"name":"Consta Testnet","explorer":"https://explorer-testnet.theconsta.com","api":""},"399":{"name":"Nativ3 Mainnet","explorer":"https://scan.nativ3.network","api":""},"400":{"name":"HyperonChain TestNet","explorer":"https://testnet.hyperonchain.com","api":""},"401":{"name":"Ozone Chain Testnet","explorer":"https://testnet.ozonescan.io","api":""},"411":{"name":"Pepe Chain Mainnet","explorer":"https://explorer.pepe-chain.vip","api":""},"416":{"name":"SX Network Mainnet","explorer":"https://explorer.sx.technology","api":""},"418":{"name":"LaTestnet","explorer":"https://testexplorer.lachain.network","api":""},"420":{"name":"Optimism Goerli Testnet","explorer":"https://optimism-goerli.blockscout.com","api":""},"424":{"name":"PGN (Public Goods Network)","explorer":"https://explorer.publicgoods.network","api":""},"444":{"name":"Synapse Chain Testnet","explorer":"https://sepolia.synapsescan.com","api":""},"456":{"name":"ARZIO Chain","explorer":"https://scan.arzio.co","api":""},"512":{"name":"Double-A Chain Mainnet","explorer":"https://scan.acuteangle.com","api":""},"513":{"name":"Double-A Chain Testnet","explorer":"https://scan-testnet.acuteangle.com","api":""},"520":{"name":"XT Smart Chain Mainnet","explorer":"https://xscscan.pub","api":""},"530":{"name":"F(x)Core Mainnet Network","explorer":"https://fx-evm.functionx.io","api":""},"534":{"name":"Candle","explorer":"https://candleexplorer.com","api":""},"555":{"name":"Vela1 Chain Mainnet","explorer":"https://exp.velaverse.io","api":""},"568":{"name":"Dogechain Testnet","explorer":"https://explorer-testnet.dogechain.dog","api":""},"570":{"name":"Rollux Mainnet","explorer":"https://explorer.rollux.com","api":""},"588":{"name":"Metis Stardust Testnet","explorer":"https://stardust-explorer.metis.io","api":""},"595":{"name":"Acala Mandala Testnet TC9","explorer":"https://blockscout.mandala.aca-staging.network","api":""},"596":{"name":"Karura Network Testnet","explorer":"https://blockscout.karura-testnet.aca-staging.network","api":""},"597":{"name":"Acala Network Testnet","explorer":"https://blockscout.acala-dev.aca-dev.network","api":""},"599":{"name":"Metis Goerli Testnet","explorer":"https://goerli.explorer.metisdevops.link","api":""},"647":{"name":"SX Network Testnet","explorer":"https://explorer.toronto.sx.technology","api":""},"648":{"name":"Endurance Smart Chain Mainnet","explorer":"https://explorer.endurance.fusionist.io","api":""},"667":{"name":"LAOS Arrakis","explorer":"https://arrakis.gorengine.com","api":""},"668":{"name":"JuncaChain","explorer":"https://scan.juncachain.com","api":""},"669":{"name":"JuncaChain testnet","explorer":"https://scan-testnet.juncachain.com","api":""},"686":{"name":"Karura Network","explorer":"https://blockscout.karura.network","api":""},"700":{"name":"Star Social Testnet","explorer":"https://avastar.info","api":""},"707":{"name":"BlockChain Station Mainnet","explorer":"https://explorer.bcsdev.io","api":""},"708":{"name":"BlockChain Station Testnet","explorer":"https://testnet.bcsdev.io","api":""},"710":{"name":"Highbury","explorer":"https://explorer.furya.io","api":""},"719":{"name":"Shibarium Beta","explorer":"https://puppyscan.shib.io","api":""},"721":{"name":"Lycan Chain","explorer":"https://explorer.lycanchain.com","api":""},"741":{"name":"Vention Smart Chain Testnet","explorer":"https://testnet.ventionscan.io","api":""},"766":{"name":"QL1","explorer":"https://mainnet.qom.one","api":""},"786":{"name":"MAAL Chain","explorer":"https://maalscan.io","api":""},"787":{"name":"Acala Network","explorer":"https://blockscout.acala.network","api":""},"788":{"name":"Aerochain Testnet","explorer":"https://testnet.aeroscan.id","api":""},"789":{"name":"Patex","explorer":"https://patexscan.io","api":""},"818":{"name":"BeOne Chain Mainnet","explorer":"https://beonescan.com","api":""},"868":{"name":"Fantasia Chain Mainnet","explorer":"https://explorer.fantasiachain.com","api":""},"876":{"name":"Bandai Namco Research Verse Mainnet","explorer":"https://explorer.main.oasvrs.bnken.net","api":""},"877":{"name":"Dexit Network","explorer":"https://dxtscan.com","api":""},"900":{"name":"Garizon Testnet Stage0","explorer":"https://explorer-testnet.garizon.com","api":""},"901":{"name":"Garizon Testnet Stage1","explorer":"https://explorer-testnet.garizon.com","api":""},"902":{"name":"Garizon Testnet Stage2","explorer":"https://explorer-testnet.garizon.com","api":""},"903":{"name":"Garizon Testnet Stage3","explorer":"https://explorer-testnet.garizon.com","api":""},"927":{"name":"Yidark Chain Mainnet","explorer":"https://yidarkscan.com","api":""},"943":{"name":"PulseChain Testnet v4","explorer":"https://scan.v4.testnet.pulsechain.com","api":""},"963":{"name":"BTC20 Smart Chain","explorer":"https://scan.bitcoincode.technology","api":""},"985":{"name":"Memo Smart Chain Mainnet","explorer":"https://scan.metamemo.one:8080","api":""},"990":{"name":"eLiberty Mainnet","explorer":"https://explorer.eliberty.ngo","api":""},"1000":{"name":"GTON Mainnet","explorer":"https://explorer.gton.network","api":""},"1001":{"name":"Klaytn Testnet Baobab","explorer":"https://scope.klaytn.com","api":""},"1003":{"name":"Tectum Emission Token","explorer":"https://explorer.tectum.io","api":""},"1004":{"name":"T-EKTA","explorer":"https://test.ektascan.io","api":""},"1031":{"name":"Proxy Network Testnet","explorer":"http://testnet-explorer.theproxy.network","api":""},"1071":{"name":"ShimmerEVM Testnet Deprecated","explorer":"https://explorer.evm.testnet.shimmer.network","api":""},"1072":{"name":"ShimmerEVM Testnet","explorer":"https://explorer.evm.testnet.shimmer.network","api":""},"1079":{"name":"Mintara Testnet","explorer":"https://subnets-test.avax.network/mintara","api":""},"1080":{"name":"Mintara Mainnet","explorer":"https://subnets.avax.network/mintara","api":""},"1088":{"name":"Metis Andromeda Mainnet","explorer":"https://andromeda-explorer.metis.io","api":""},"1101":{"name":"Polygon zkEVM","explorer":"https://zkevm.polygonscan.com","api":""},"1108":{"name":"BLXq Mainnet","explorer":"https://explorer.blxq.org","api":""},"1111":{"name":"WEMIX3.0 Mainnet","explorer":"https://explorer.wemix.com","api":""},"1112":{"name":"WEMIX3.0 Testnet","explorer":"https://microscope.test.wemix.com","api":""},"1115":{"name":"Core Blockchain Testnet","explorer":"https://scan.test.btcs.network","api":""},"1116":{"name":"Core Blockchain Mainnet","explorer":"https://scan.coredao.org","api":""},"1117":{"name":"Dogcoin Mainnet","explorer":"https://explorer.dogcoin.network","api":""},"1133":{"name":"DeFiMetaChain","explorer":"https://meta.defiscan.live","api":""},"1138":{"name":"AmStar Testnet","explorer":"https://testnet.amstarscan.com","api":""},"1149":{"name":"Symplexia Smart Chain","explorer":"https://explorer.plexfinance.us","api":""},"1177":{"name":"Smart Host Teknoloji TESTNET","explorer":"https://s2.tl.web.tr:4000","api":""},"1197":{"name":"Iora Chain","explorer":"https://explorer.iorachain.com","api":""},"1202":{"name":"World Trade Technical Chain Mainnet","explorer":"https://explorer.cadaut.com","api":""},"1214":{"name":"EnterChain Mainnet","explorer":"https://explorer.entercoin.net","api":""},"1229":{"name":"Exzo Network Mainnet","explorer":"https://exzoscan.io","api":""},"1234":{"name":"Step Network","explorer":"https://stepscan.io","api":""},"1252":{"name":"CIC Chain Testnet","explorer":"https://testnet.cicscan.com","api":""},"1311":{"name":"Dos Fuji Subnet","explorer":"https://test.doscan.io","api":""},"1314":{"name":"Alyx Mainnet","explorer":"https://www.alyxscan.com","api":""},"1319":{"name":"AIA Mainnet","explorer":"https://aiascan.com","api":""},"1320":{"name":"AIA Testnet","explorer":"https://testnet.aiascan.com","api":""},"1343":{"name":"Blitz Subnet","explorer":"https://subnets-test.avax.network/blitz","api":""},"1353":{"name":"CIC Chain Mainnet","explorer":"https://cicscan.com","api":""},"1379":{"name":"Kalar Chain","explorer":"https://explorer.kalarchain.tech","api":""},"1388":{"name":"AmStar Mainnet","explorer":"https://mainnet.amstarscan.com","api":""},"1392":{"name":"Joseon Mainnet","explorer":"https://www.blockexplorer.com","api":""},"1402":{"name":"Polygon zkEVM Testnet old","explorer":"https://explorer.public.zkevm-test.net","api":""},"1422":{"name":"Polygon zkEVM Testnet Pre Audit-Upgraded","explorer":"https://explorer.public.zkevm-test.net","api":""},"1433":{"name":"Rikeza Network Mainnet","explorer":"https://rikscan.com","api":""},"1442":{"name":"Polygon zkEVM Testnet","explorer":"https://explorer.public.zkevm-test.net","api":""},"1452":{"name":"GIL Testnet","explorer":"https://explorer.giltestnet.com","api":""},"1515":{"name":"Beagle Messaging Chain","explorer":"https://eth.beagle.chat","api":""},"1559":{"name":"Tenet","explorer":"https://tenetscan.io","api":""},"1663":{"name":"Horizen Gobi Testnet","explorer":"https://gobi-explorer.horizen.io","api":""},"1701":{"name":"Anytype EVM Chain","explorer":"https://explorer.anytype.io","api":""},"1707":{"name":"TBSI Mainnet","explorer":"https://exp.blockchain.or.th","api":""},"1708":{"name":"TBSI Testnet","explorer":"https://exp.testnet.blockchain.or.th","api":""},"1773":{"name":"PartyChain","explorer":"https://partyexplorer.co","api":""},"1777":{"name":"Gauss Mainnet","explorer":"https://explorer.gaussgang.com","api":""},"1804":{"name":"Kerleano","explorer":"https://ethereum-pocr.github.io/explorer/kerleano","api":""},"1818":{"name":"Cube Chain Mainnet","explorer":"https://cubescan.network","api":""},"1819":{"name":"Cube Chain Testnet","explorer":"https://testnet.cubescan.network","api":""},"1875":{"name":"WhiteBIT Network","explorer":"https://explorer.whitebit.network","api":""},"1881":{"name":"Gitshock Cartenz Testnet","explorer":"https://scan.cartenz.works","api":""},"1890":{"name":"Lightlink Phoenix Mainnet","explorer":"https://phoenix.lightlink.io","api":""},"1891":{"name":"Lightlink Pegasus Testnet","explorer":"https://pegasus.lightlink.io","api":""},"1898":{"name":"BON Network","explorer":"https://explorer.boyanet.org:4001","api":""},"1904":{"name":"Sports Chain Network","explorer":"https://explorer.sportschainnetwork.xyz","api":""},"1907":{"name":"Bitcichain Mainnet","explorer":"https://bitciexplorer.com","api":""},"1908":{"name":"Bitcichain Testnet","explorer":"https://testnet.bitciexplorer.com","api":""},"1945":{"name":"ONUS Chain Testnet","explorer":"https://explorer-testnet.onuschain.io","api":""},"1954":{"name":"Dexilla Testnet","explorer":"https://exp.dexilla.com","api":""},"1967":{"name":"Eleanor","explorer":"https://explorer.metatime.com/eleanor","api":""},"1969":{"name":"Super Smart Chain Testnet","explorer":"https://testnetscan.scschain.com","api":""},"1970":{"name":"Super Smart Chain Mainnet","explorer":"https://scan.scschain.com","api":""},"1975":{"name":"ONUS Chain Mainnet","explorer":"https://explorer.onuschain.io","api":""},"1994":{"name":"Ekta","explorer":"https://ektascan.io","api":""},"1995":{"name":"edeXa Testnet","explorer":"https://explorer.testnet.edexa.com","api":""},"2000":{"name":"Dogechain Mainnet","explorer":"https://explorer.dogechain.dog","api":""},"2016":{"name":"MainnetZ Mainnet","explorer":"https://explorer.mainnetz.io","api":""},"2018":{"name":"PublicMint Devnet","explorer":"https://explorer.dev.publicmint.io","api":""},"2019":{"name":"PublicMint Testnet","explorer":"https://explorer.tst.publicmint.io","api":""},"2020":{"name":"PublicMint Mainnet","explorer":"https://explorer.publicmint.io","api":""},"2021":{"name":"Edgeware EdgeEVM Mainnet","explorer":"https://edgscan.live","api":""},"2022":{"name":"Beresheet BereEVM Testnet","explorer":"https://testnet.edgscan.live","api":""},"2031":{"name":"Centrifuge","explorer":"https://centrifuge.subscan.io","api":""},"2037":{"name":"Kiwi Subnet","explorer":"https://subnets-test.avax.network/kiwi","api":""},"2038":{"name":"Shrapnel Testnet","explorer":"https://subnets-test.avax.network/shrapnel","api":""},"2077":{"name":"Quokkacoin Mainnet","explorer":"https://explorer.qkacoin.org","api":""},"2100":{"name":"Ecoball Mainnet","explorer":"https://scan.ecoball.org","api":""},"2101":{"name":"Ecoball Testnet Espuma","explorer":"https://espuma-scan.ecoball.org","api":""},"2109":{"name":"Exosama Network","explorer":"https://explorer.exosama.com","api":""},"2122":{"name":"Metaplayerone Mainnet","explorer":"https://scan.metaplayer.one","api":""},"2124":{"name":"Metaplayerone Dubai Testnet","explorer":"https://dubai.mp1scan.io","api":""},"2151":{"name":"BOSagora Mainnet","explorer":"https://boascan.io","api":""},"2152":{"name":"Findora Mainnet","explorer":"https://evm.findorascan.io","api":""},"2153":{"name":"Findora Testnet","explorer":"https://testnet-anvil.evm.findorascan.io","api":""},"2154":{"name":"Findora Forge","explorer":"https://testnet-forge.evm.findorascan.io","api":""},"2199":{"name":"Moonsama Network","explorer":"https://explorer.moonsama.com","api":""},"2202":{"name":"Antofy Mainnet","explorer":"https://antofyscan.com","api":""},"2221":{"name":"Kava Testnet","explorer":"http://testnet.kavascan.com","api":""},"2222":{"name":"Kava","explorer":"https://kavascan.com","api":""},"2223":{"name":"VChain Mainnet","explorer":"https://scan.vcex.xyz","api":""},"2300":{"name":"BOMB Chain","explorer":"https://bombscan.com","api":""},"2357":{"name":"(deprecated) Kroma Sepolia","explorer":"https://blockscout.sepolia-deprecated.kroma.network","api":""},"2358":{"name":"Kroma Sepolia","explorer":"https://blockscout.sepolia.kroma.network","api":""},"2399":{"name":"BOMB Chain Testnet","explorer":"https://explorer.bombchain-testnet.ankr.com","api":""},"2400":{"name":"TCG Verse Mainnet","explorer":"https://explorer.tcgverse.xyz","api":""},"2415":{"name":"XODEX","explorer":"https://explorer.xo-dex.com","api":""},"2484":{"name":"Unicorn Ultra Nebulas Testnet","explorer":"https://testnet.u2uscan.xyz","api":""},"2569":{"name":"TechPay Mainnet","explorer":"https://tpcscan.com","api":""},"2606":{"name":"PoCRNet","explorer":"https://ethereum-pocr.github.io/explorer/pocrnet","api":""},"2611":{"name":"Redlight Chain Mainnet","explorer":"https://redlightscan.finance","api":""},"2612":{"name":"EZChain C-Chain Mainnet","explorer":"https://cchain-explorer.ezchain.com","api":""},"2613":{"name":"EZChain C-Chain Testnet","explorer":"https://testnet-cchain-explorer.ezchain.com","api":""},"2625":{"name":"WhiteBIT Network Testnet","explorer":"https://explorer.whitebit.network/testnet","api":""},"2710":{"name":"Morphism Testnet","explorer":"https://explorer-testnet.morphism.xyz","api":""},"3011":{"name":"PLAYA3ULL GAMES","explorer":"https://3011.routescan.io","api":""},"3031":{"name":"Orlando Chain","explorer":"https://orlscan.com","api":""},"3068":{"name":"Bifrost Mainnet","explorer":"https://explorer.mainnet.thebifrost.io","api":""},"3306":{"name":"Debounce Subnet Testnet","explorer":"https://explorer.debounce.network","api":""},"3333":{"name":"Web3Q Testnet","explorer":"https://explorer.testnet.web3q.io","api":""},"3334":{"name":"Web3Q Galileo","explorer":"https://explorer.galileo.web3q.io","api":""},"3400":{"name":"Paribu Net Mainnet","explorer":"https://explorer.paribu.network","api":""},"3434":{"name":"SecureChain Testnet","explorer":"https://testnet.securechain.ai","api":""},"3500":{"name":"Paribu Net Testnet","explorer":"https://testnet.paribuscan.com","api":""},"3501":{"name":"JFIN Chain","explorer":"https://exp.jfinchain.com","api":""},"3636":{"name":"Botanix Testnet","explorer":"https://3xpl.com/botanix","api":""},"3637":{"name":"Botanix Mainnet","explorer":"https://btxtestchain.com","api":""},"3639":{"name":"iChain Network","explorer":"https://ichainscan.com","api":""},"3666":{"name":"Jouleverse Mainnet","explorer":"https://jscan.jnsdao.com","api":""},"3690":{"name":"Bittex Mainnet","explorer":"https://bittexscan.com","api":""},"3698":{"name":"SenjePowers Testnet","explorer":"https://testnet.senjepowersscan.com","api":""},"3699":{"name":"SenjePowers Mainnet","explorer":"https://senjepowersscan.com","api":""},"3737":{"name":"Crossbell","explorer":"https://scan.crossbell.io","api":""},"3797":{"name":"AlveyChain Mainnet","explorer":"https://alveyscan.com","api":""},"3888":{"name":"KalyChain Mainnet","explorer":"https://kalyscan.io","api":""},"3889":{"name":"KalyChain Testnet","explorer":"https://testnet.kalyscan.io","api":""},"3912":{"name":"DRAC Network","explorer":"https://www.dracscan.io","api":""},"3939":{"name":"DOS Tesnet","explorer":"https://test.doscan.io","api":""},"3966":{"name":"DYNO Mainnet","explorer":"https://dynoscan.io","api":""},"3967":{"name":"DYNO Testnet","explorer":"https://testnet.dynoscan.io","api":""},"4000":{"name":"Ozone Chain Mainnet","explorer":"https://ozonescan.io","api":""},"4001":{"name":"Peperium Chain Testnet","explorer":"https://scan-testnet.peperium.io","api":""},"4002":{"name":"Fantom Testnet","explorer":"https://testnet.ftmscan.com","api":""},"4062":{"name":"Nahmii 3 Testnet","explorer":"https://explorer.testnet.n3.nahmii.io","api":""},"4096":{"name":"Bitindi Testnet","explorer":"https://testnet.bitindiscan.com","api":""},"4099":{"name":"Bitindi Mainnet","explorer":"https://bitindiscan.com","api":""},"4102":{"name":"AIOZ Network Testnet","explorer":"https://testnet.explorer.aioz.network","api":""},"4141":{"name":"Tipboxcoin Testnet","explorer":"https://testnet.tipboxcoin.net","api":""},"4242":{"name":"Nexi Mainnet","explorer":"https://www.nexiscan.com","api":""},"4337":{"name":"Beam","explorer":"https://subnets.avax.network/beam","api":""},"4400":{"name":"Credit Smart Chain Mainnet","explorer":"https://scan.creditsmartchain.com","api":""},"4460":{"name":"Orderly Sepolia Testnet","explorer":"https://explorerl2new-orderly-l2-4460-sepolia-8tc3sd7dvy.t.conduit.xyz","api":""},"4689":{"name":"IoTeX Network Mainnet","explorer":"https://iotexscan.io","api":""},"4690":{"name":"IoTeX Network Testnet","explorer":"https://testnet.iotexscan.io","api":""},"4777":{"name":"BlackFort Exchange Network Testnet","explorer":"https://testnet-explorer.blackfort.network","api":""},"4918":{"name":"Venidium Testnet","explorer":"https://evm-testnet.venidiumexplorer.com","api":""},"4919":{"name":"Venidium Mainnet","explorer":"https://evm.venidiumexplorer.com","api":""},"4999":{"name":"BlackFort Exchange Network","explorer":"https://explorer.blackfort.network","api":""},"5000":{"name":"Mantle","explorer":"https://explorer.mantle.xyz","api":""},"5001":{"name":"Mantle Testnet","explorer":"https://explorer.testnet.mantle.xyz","api":""},"5003":{"name":"Mantle Sepolia Testnet","explorer":"https://explorer.sepolia.mantle.xyz","api":""},"5234":{"name":"Humanode Mainnet","explorer":"https://humanode.subscan.io","api":""},"5522":{"name":"VEX EVM TESTNET","explorer":"https://testnet.vexascan.com/evmexplorer","api":""},"5551":{"name":"Nahmii Mainnet","explorer":"https://explorer.nahmii.io","api":""},"5553":{"name":"Nahmii Testnet","explorer":"https://explorer.testnet.nahmii.io","api":""},"5555":{"name":"Chain Verse Mainnet","explorer":"https://explorer.chainverse.info","api":""},"5611":{"name":"opBNB Testnet","explorer":"https://opbnb-testnet.bscscan.com","api":""},"5700":{"name":"Syscoin Tanenbaum Testnet","explorer":"https://tanenbaum.io","api":""},"5758":{"name":"SatoshiChain Testnet","explorer":"https://testnet.satoshiscan.io","api":""},"5851":{"name":"Ontology Testnet","explorer":"https://explorer.ont.io/testnet","api":""},"5869":{"name":"Wegochain Rubidium Mainnet","explorer":"https://scan2.wegochain.io","api":""},"6065":{"name":"Tres Testnet","explorer":"https://explorer-test.tresleches.finance","api":""},"6066":{"name":"Tres Mainnet","explorer":"https://explorer.tresleches.finance","api":""},"6118":{"name":"UPTN Testnet","explorer":"https://testnet.explorer.uptn.io","api":""},"6119":{"name":"UPTN","explorer":"https://explorer.uptn.io","api":""},"6552":{"name":"Scolcoin WeiChain Testnet","explorer":"https://testnet-explorer.scolcoin.com","api":""},"6789":{"name":"Gold Smart Chain Mainnet","explorer":"https://mainnet.goldsmartchain.com","api":""},"7027":{"name":"Ella the heart","explorer":"https://ella.network","api":""},"7171":{"name":"Bitrock Mainnet","explorer":"https://explorer.bit-rock.io","api":""},"7332":{"name":"Horizen EON Mainnet","explorer":"https://eon-explorer.horizenlabs.io","api":""},"7341":{"name":"Shyft Mainnet","explorer":"https://bx.shyft.network","api":""},"7575":{"name":"ADIL Testnet","explorer":"https://testnet.adilchain-scan.io","api":""},"7576":{"name":"Adil Chain V2 Mainnet","explorer":"https://adilchain-scan.io","api":""},"7668":{"name":"The Root Network - Mainnet","explorer":"https://explorer.rootnet.live","api":""},"7672":{"name":"The Root Network - Porcini Testnet","explorer":"https://explorer.rootnet.cloud","api":""},"7771":{"name":"Bitrock Testnet","explorer":"https://testnetscan.bit-rock.io","api":""},"7979":{"name":"DOS Chain","explorer":"https://doscan.io","api":""},"8080":{"name":"Shardeum Liberty 1.X","explorer":"https://explorer-liberty10.shardeum.org","api":""},"8081":{"name":"Shardeum Liberty 2.X","explorer":"https://explorer-liberty20.shardeum.org","api":""},"8082":{"name":"Shardeum Sphinx 1.X","explorer":"https://explorer-sphinx.shardeum.org","api":""},"8192":{"name":"Torus Mainnet","explorer":"https://toruscan.com","api":""},"8194":{"name":"Torus Testnet","explorer":"https://testnet.torusscan.com","api":""},"8668":{"name":"Hela Official Runtime Mainnet","explorer":"https://mainnet-blockexplorer.helachain.com","api":""},"8723":{"name":"TOOL Global Mainnet","explorer":"https://www.olo.network","api":""},"8738":{"name":"Alph Network","explorer":"https://explorer.alph.network","api":""},"8888":{"name":"XANAChain","explorer":"https://xanachain.xana.net","api":""},"8898":{"name":"Mammoth Mainnet","explorer":"https://mmtscan.io","api":""},"8899":{"name":"JIBCHAIN L1","explorer":"https://exp-l1.jibchain.net","api":""},"8989":{"name":"Giant Mammoth Mainnet","explorer":"https://scan.gmmtchain.io","api":""},"9012":{"name":"BerylBit Mainnet","explorer":"https://explorer.berylbit.io","api":""},"9223":{"name":"Codefin Mainnet","explorer":"https://explorer.codefin.pro","api":""},"9339":{"name":"Dogcoin Testnet","explorer":"https://testnet.dogcoin.network","api":""},"9528":{"name":"QEasyWeb3 Testnet","explorer":"https://www.qeasyweb3.com","api":""},"9559":{"name":"Neonlink Testnet","explorer":"https://testnet-scan.neonlink.io","api":""},"9768":{"name":"MainnetZ Testnet","explorer":"https://testnet.mainnetz.io","api":""},"9977":{"name":"Mind Smart Chain Testnet","explorer":"https://testnet.mindscan.info","api":""},"9996":{"name":"Mind Smart Chain Mainnet","explorer":"https://mainnet.mindscan.info","api":""},"9997":{"name":"AltLayer Testnet","explorer":"https://testnet-rollup-explorer.altlayer.io","api":""},"10081":{"name":"Japan Open Chain Testnet","explorer":"https://explorer.testnet.japanopenchain.org","api":""},"10200":{"name":"Gnosis Chiado Testnet","explorer":"https://blockscout.chiadochain.net","api":""},"10201":{"name":"MaxxChain Mainnet","explorer":"https://explorer.maxxchain.org","api":""},"10243":{"name":"Arthera Testnet","explorer":"https://explorer-test.arthera.net","api":""},"10395":{"name":"Worldland Testnet","explorer":"https://testscan.worldland.foundation","api":""},"10507":{"name":"Numbers Mainnet","explorer":"https://mainnet.num.network","api":""},"10508":{"name":"Numbers Testnet","explorer":"https://testnet.num.network","api":""},"10823":{"name":"CryptoCoinPay","explorer":"https://cryptocoinpay.info","api":""},"10946":{"name":"Quadrans Blockchain","explorer":"https://explorer.quadrans.io","api":""},"10947":{"name":"Quadrans Blockchain Testnet","explorer":"https://explorer.testnet.quadrans.io","api":""},"11111":{"name":"WAGMI","explorer":"https://subnets-test.avax.network/wagmi","api":""},"11115":{"name":"Astra Testnet","explorer":"https://explorer.astranaut.dev","api":""},"11119":{"name":"HashBit Mainnet","explorer":"https://explorer.hashbit.org","api":""},"11235":{"name":"Haqq Network","explorer":"https://explorer.haqq.network","api":""},"11437":{"name":"Shyft Testnet","explorer":"https://bx.testnet.shyft.network","api":""},"11612":{"name":"Sardis Testnet","explorer":"https://testnet.sardisnetwork.com","api":""},"11891":{"name":"Polygon Supernet Arianee","explorer":"https://polygonsupernet.explorer.arianee.net","api":""},"12009":{"name":"SatoshiChain Mainnet","explorer":"https://satoshiscan.io","api":""},"12051":{"name":"Singularity ZERO Testnet","explorer":"https://betaenv.singularity.gold:18002","api":""},"12052":{"name":"Singularity ZERO Mainnet","explorer":"https://zeroscan.singularity.gold","api":""},"12123":{"name":"BRC Chain Mainnet","explorer":"https://scan.brcchain.io","api":""},"12306":{"name":"Fibonacci Mainnet","explorer":"https://scan.fibochain.org","api":""},"12345":{"name":"Step Testnet","explorer":"https://testnet.stepscan.io","api":""},"12715":{"name":"Rikeza Network Testnet","explorer":"https://testnet.rikscan.com","api":""},"12890":{"name":"Quantum Chain Testnet","explorer":"https://testnet.quantumscan.org","api":""},"13000":{"name":"SPS","explorer":"http://spsscan.ssquad.games","api":""},"13308":{"name":"Credit Smart Chain","explorer":"https://scan.creditsmartchain.com","api":""},"13337":{"name":"Beam Testnet","explorer":"https://subnets-test.avax.network/beam","api":""},"13381":{"name":"Phoenix Mainnet","explorer":"https://phoenixplorer.com","api":""},"14000":{"name":"SPS Testnet","explorer":"https://explorer.3sps.net","api":""},"15555":{"name":"Trust EVM Testnet","explorer":"https://trustscan.one","api":""},"15557":{"name":"EOS EVM Network Testnet","explorer":"https://explorer.testnet.evm.eosnetwork.com","api":""},"16507":{"name":"Genesys Mainnet","explorer":"https://gchainexplorer.genesys.network","api":""},"16888":{"name":"IVAR Chain Testnet","explorer":"https://testnet.ivarscan.com","api":""},"17000":{"name":"Holesky","explorer":"https://holesky.beaconcha.in","api":""},"17171":{"name":"G8Chain Mainnet","explorer":"https://mainnet.oneg8.network","api":""},"17777":{"name":"EOS EVM Network","explorer":"https://explorer.evm.eosnetwork.com","api":""},"18000":{"name":"Frontier of Dreams Testnet","explorer":"https://explorer.fod.games","api":""},"18159":{"name":"Proof Of Memes","explorer":"https://memescan.io","api":""},"18181":{"name":"G8Chain Testnet","explorer":"https://testnet.oneg8.network","api":""},"18686":{"name":"MXC zkEVM Mainnet","explorer":"https://explorer.mxc.com","api":""},"19011":{"name":"HOME Verse Mainnet","explorer":"https://explorer.oasys.homeverse.games","api":""},"20001":{"name":"Camelark Mainnet","explorer":"https://scan.camelark.com","api":""},"20736":{"name":"P12 Chain","explorer":"https://explorer.p12.games","api":""},"21816":{"name":"omChain Mainnet","explorer":"https://explorer.omchain.io","api":""},"22222":{"name":"Nautilus Mainnet","explorer":"https://nautscan.com","api":""},"22776":{"name":"MAP Mainnet","explorer":"https://mapscan.io","api":""},"23006":{"name":"Antofy Testnet","explorer":"https://test.antofyscan.com","api":""},"23118":{"name":"Opside Testnet","explorer":"https://opside.info","api":""},"23294":{"name":"Oasis Sapphire","explorer":"https://explorer.sapphire.oasis.io","api":""},"23295":{"name":"Oasis Sapphire Testnet","explorer":"https://testnet.explorer.sapphire.oasis.dev","api":""},"26600":{"name":"Hertz Network Mainnet","explorer":"https://hertzscan.com","api":""},"26863":{"name":"OasisChain Mainnet","explorer":"https://scan.oasischain.io","api":""},"28528":{"name":"Optimism Bedrock (Goerli Alpha Testnet)","explorer":"https://blockscout.com/optimism/bedrock-alpha","api":""},"29548":{"name":"MCH Verse Mainnet","explorer":"https://explorer.oasys.mycryptoheroes.net","api":""},"30067":{"name":"Piece testnet","explorer":"https://testnet-scan.piecenetwork.com","api":""},"31223":{"name":"CloudTx Mainnet","explorer":"https://scan.cloudtx.finance","api":""},"31224":{"name":"CloudTx Testnet","explorer":"https://explorer.cloudtx.finance","api":""},"31337":{"name":"GoChain Testnet","explorer":"https://testnet-explorer.gochain.io","api":""},"32520":{"name":"Bitgert Mainnet","explorer":"https://brisescan.com","api":""},"32659":{"name":"Fusion Mainnet","explorer":"https://fsnscan.com","api":""},"33210":{"name":"Cloudverse Subnet","explorer":"https://subnets.avax.network/cloudverse","api":""},"33333":{"name":"Aves Mainnet","explorer":"https://avescan.io","api":""},"33385":{"name":"Zilliqa EVM Devnet","explorer":"https://otterscan.devnet.zilliqa.com","api":""},"33469":{"name":"Zilliqa 2 EVM Devnet","explorer":"https://explorer.zq2-devnet.zilstg.dev","api":""},"35011":{"name":"J2O Taro","explorer":"https://exp.j2o.io","api":""},"35441":{"name":"Q Mainnet","explorer":"https://explorer.q.org","api":""},"35443":{"name":"Q Testnet","explorer":"https://explorer.qtestnet.org","api":""},"39815":{"name":"OHO Mainnet","explorer":"https://ohoscan.com","api":""},"42161":{"name":"Arbitrum One","explorer":"https://arbiscan.io","api":""},"42170":{"name":"Arbitrum Nova","explorer":"https://nova-explorer.arbitrum.io","api":""},"42220":{"name":"Celo Mainnet","explorer":"https://celoscan.io","api":""},"42261":{"name":"Oasis Emerald Testnet","explorer":"https://testnet.explorer.emerald.oasis.dev","api":""},"42262":{"name":"Oasis Emerald","explorer":"https://explorer.emerald.oasis.dev","api":""},"42801":{"name":"Gesoten Verse Testnet","explorer":"https://explorer.testnet.verse.gesoten.com","api":""},"42888":{"name":"Kinto Testnet","explorer":"http://35.215.120.180:4000","api":""},"43113":{"name":"Avalanche Fuji Testnet","explorer":"https://testnet.snowtrace.io","api":""},"43114":{"name":"Avalanche C-Chain","explorer":"https://snowtrace.io","api":""},"44444":{"name":"Frenchain","explorer":"https://frenscan.io","api":""},"44787":{"name":"Celo Alfajores Testnet","explorer":"https://alfajores.celoscan.io","api":""},"45000":{"name":"Autobahn Network","explorer":"https://explorer.autobahn.network","api":""},"46688":{"name":"Fusion Testnet","explorer":"https://testnet.fsnscan.com","api":""},"49049":{"name":"Wireshape Floripa Testnet","explorer":"https://floripa-explorer.wireshape.org","api":""},"49088":{"name":"Bifrost Testnet","explorer":"https://explorer.testnet.thebifrost.io","api":""},"50021":{"name":"GTON Testnet","explorer":"https://explorer.testnet.gton.network","api":""},"51178":{"name":"Lumoz Testnet Alpha","explorer":"https://lumoz.info","api":""},"51712":{"name":"Sardis Mainnet","explorer":"https://contract-mainnet.sardisnetwork.com","api":""},"52014":{"name":"Electroneum Mainnet","explorer":"https://blockexplorer.electroneum.com","api":""},"54211":{"name":"Haqq Chain Testnet","explorer":"https://explorer.testedge2.haqq.network","api":""},"55004":{"name":"Titan","explorer":"https://explorer.titan.tokamak.network","api":""},"55555":{"name":"REI Chain Mainnet","explorer":"https://reiscan.com","api":""},"55556":{"name":"REI Chain Testnet","explorer":"https://testnet.reiscan.com","api":""},"56789":{"name":"VELO Labs Mainnet","explorer":"https://novascan.velo.org","api":""},"57000":{"name":"Rollux Testnet","explorer":"https://rollux.tanenbaum.io","api":""},"58008":{"name":"Sepolia PGN (Public Goods Network)","explorer":"https://explorer.sepolia.publicgoods.network","api":""},"59140":{"name":"Linea Testnet","explorer":"https://goerli.lineascan.build","api":""},"59144":{"name":"Linea","explorer":"https://lineascan.build","api":""},"60000":{"name":"Thinkium Testnet Chain 0","explorer":"https://test0.thinkiumscan.net","api":""},"60001":{"name":"Thinkium Testnet Chain 1","explorer":"https://test1.thinkiumscan.net","api":""},"60002":{"name":"Thinkium Testnet Chain 2","explorer":"https://test2.thinkiumscan.net","api":""},"60103":{"name":"Thinkium Testnet Chain 103","explorer":"https://test103.thinkiumscan.net","api":""},"61800":{"name":"AxelChain Dev-Net","explorer":"https://devexplorer2.viacube.com","api":""},"61803":{"name":"Etica Mainnet","explorer":"https://eticascan.org","api":""},"61916":{"name":"DoKEN Super Chain Mainnet","explorer":"https://explore.doken.dev","api":""},"63000":{"name":"eCredits Mainnet","explorer":"https://explorer.ecredits.com","api":""},"63001":{"name":"eCredits Testnet","explorer":"https://explorer.tst.ecredits.com","api":""},"65450":{"name":"Scolcoin Mainnet","explorer":"https://explorer.scolcoin.com","api":""},"67390":{"name":"SiriusNet","explorer":"https://siriusnet.tryethernal.com","api":""},"68770":{"name":"DM2 Verse Mainnet","explorer":"https://explorer.dm2verse.dmm.com","api":""},"70000":{"name":"Thinkium Mainnet Chain 0","explorer":"https://chain0.thinkiumscan.net","api":""},"70001":{"name":"Thinkium Mainnet Chain 1","explorer":"https://chain1.thinkiumscan.net","api":""},"70002":{"name":"Thinkium Mainnet Chain 2","explorer":"https://chain2.thinkiumscan.net","api":""},"70103":{"name":"Thinkium Mainnet Chain 103","explorer":"https://chain103.thinkiumscan.net","api":""},"73927":{"name":"Mixin Virtual Machine","explorer":"https://scan.mvm.dev","api":""},"77238":{"name":"Foundry Chain Testnet","explorer":"https://testnet-explorer.foundryscan.org","api":""},"77612":{"name":"Vention Smart Chain Mainnet","explorer":"https://ventionscan.io","api":""},"78281":{"name":"Dragonfly Mainnet (Hexapod)","explorer":"https://blockscout.dragonfly.hexapod.network","api":""},"78430":{"name":"Amplify Subnet","explorer":"https://subnets-test.avax.network/amplify","api":""},"78431":{"name":"Bulletin Subnet","explorer":"https://subnets-test.avax.network/bulletin","api":""},"78432":{"name":"Conduit Subnet","explorer":"https://subnets-test.avax.network/conduit","api":""},"79879":{"name":"Gold Smart Chain Testnet","explorer":"https://testnet.goldsmartchain.com","api":""},"80001":{"name":"Mumbai","explorer":"https://mumbai.polygonscan.com","api":""},"81720":{"name":"Quantum Chain Mainnet","explorer":"https://quantumscan.org","api":""},"84532":{"name":"Base Sepolia Testnet","explorer":"https://base-sepolia.blockscout.com","api":""},"84886":{"name":"Aerie Network","explorer":"https://explorer.aerielab.io","api":""},"88002":{"name":"Nautilus Proteus Testnet","explorer":"https://proteus.nautscan.com","api":""},"88888":{"name":"IVAR Chain Mainnet","explorer":"https://ivarscan.com","api":""},"91002":{"name":"Nautilus Trition Chain","explorer":"https://triton.nautscan.com","api":""},"92001":{"name":"Lambda Testnet","explorer":"https://explorer.lambda.top","api":""},"96970":{"name":"Mantis Testnet (Hexapod)","explorer":"https://blockscout.mantis.hexapod.network","api":""},"99099":{"name":"eLiberty Testnet","explorer":"https://testnet.eliberty.ngo","api":""},"100001":{"name":"QuarkChain Mainnet Shard 0","explorer":"https://mainnet.quarkchain.io/0","api":""},"100002":{"name":"QuarkChain Mainnet Shard 1","explorer":"https://mainnet.quarkchain.io/1","api":""},"100003":{"name":"QuarkChain Mainnet Shard 2","explorer":"https://mainnet.quarkchain.io/2","api":""},"100004":{"name":"QuarkChain Mainnet Shard 3","explorer":"https://mainnet.quarkchain.io/3","api":""},"100005":{"name":"QuarkChain Mainnet Shard 4","explorer":"https://mainnet.quarkchain.io/4","api":""},"100006":{"name":"QuarkChain Mainnet Shard 5","explorer":"https://mainnet.quarkchain.io/5","api":""},"100007":{"name":"QuarkChain Mainnet Shard 6","explorer":"https://mainnet.quarkchain.io/6","api":""},"100008":{"name":"QuarkChain Mainnet Shard 7","explorer":"https://mainnet.quarkchain.io/7","api":""},"101010":{"name":"Soverun Testnet","explorer":"https://testnet.soverun.com","api":""},"103090":{"name":"Crystaleum","explorer":"https://scan.crystaleum.org","api":""},"108801":{"name":"BROChain Mainnet","explorer":"https://explorer.brochain.org","api":""},"110001":{"name":"QuarkChain Devnet Shard 0","explorer":"https://devnet.quarkchain.io/0","api":""},"110002":{"name":"QuarkChain Devnet Shard 1","explorer":"https://devnet.quarkchain.io/1","api":""},"110003":{"name":"QuarkChain Devnet Shard 2","explorer":"https://devnet.quarkchain.io/2","api":""},"110004":{"name":"QuarkChain Devnet Shard 3","explorer":"https://devnet.quarkchain.io/3","api":""},"110005":{"name":"QuarkChain Devnet Shard 4","explorer":"https://devnet.quarkchain.io/4","api":""},"110006":{"name":"QuarkChain Devnet Shard 5","explorer":"https://devnet.quarkchain.io/5","api":""},"110007":{"name":"QuarkChain Devnet Shard 6","explorer":"https://devnet.quarkchain.io/6","api":""},"110008":{"name":"QuarkChain Devnet Shard 7","explorer":"https://devnet.quarkchain.io/7","api":""},"111000":{"name":"Siberium Test Network","explorer":"https://explorer.test.siberium.net","api":""},"111111":{"name":"Siberium Network","explorer":"https://explorer.main.siberium.net","api":""},"112358":{"name":"Metachain One Mainnet","explorer":"https://explorer.metachain.one","api":""},"123456":{"name":"ADIL Devnet","explorer":"https://devnet.adilchain-scan.io","api":""},"167004":{"name":"Taiko (Alpha-2 Testnet)","explorer":"https://explorer.a2.taiko.xyz","api":""},"167005":{"name":"Taiko Grimsvotn L2","explorer":"https://explorer.test.taiko.xyz","api":""},"167006":{"name":"Taiko Eldfell L3","explorer":"https://explorer.l3test.taiko.xyz","api":""},"167007":{"name":"Taiko Jolnir L2","explorer":"https://explorer.jolnir.taiko.xyz","api":""},"201804":{"name":"Mythical Chain","explorer":"https://explorer.mythicalgames.com","api":""},"202020":{"name":"Decimal Smart Chain Testnet","explorer":"https://testnet.explorer.decimalchain.com","api":""},"202624":{"name":"Jellie","explorer":"https://jellie.twala.io","api":""},"220315":{"name":"Mas Mainnet","explorer":"https://explorer.masnet.ai","api":""},"224168":{"name":"Taf ECO Chain Mainnet","explorer":"https://ecoscan.tafchain.com","api":""},"247253":{"name":"Saakuru Testnet","explorer":"https://explorer-testnet.saakuru.network","api":""},"271271":{"name":"EgonCoin Testnet","explorer":"https://testnet.egonscan.com","api":""},"330844":{"name":"TTcoin Smart Chain Mainnet","explorer":"https://tscscan.com","api":""},"333331":{"name":"Aves Testnet","explorer":"https://testnet.avescoin.io","api":""},"333333":{"name":"Nativ3 Testnet","explorer":"https://scantest.nativ3.network","api":""},"355113":{"name":"Bitfinity Network Testnet","explorer":"https://explorer.bitfinity.network","api":""},"381931":{"name":"Metal C-Chain","explorer":"https://metalscan.io","api":""},"381932":{"name":"Metal Tahoe C-Chain","explorer":"https://tahoe.metalscan.io","api":""},"404040":{"name":"Tipboxcoin Mainnet","explorer":"https://tipboxcoin.net","api":""},"420420":{"name":"Kekchain","explorer":"https://mainnet-explorer.kekchain.com","api":""},"420666":{"name":"Kekchain (kektest)","explorer":"https://testnet-explorer.kekchain.com","api":""},"420692":{"name":"Alterium L2 Testnet","explorer":"https://l2-testnet.altscan.org","api":""},"421611":{"name":"Arbitrum Rinkeby","explorer":"https://testnet.arbiscan.io","api":""},"421613":{"name":"Arbitrum Goerli","explorer":"https://goerli.arbiscan.io","api":""},"421614":{"name":"Arbitrum Sepolia","explorer":"https://sepolia-explorer.arbitrum.io","api":""},"432201":{"name":"Dexalot Subnet Testnet","explorer":"https://subnets-test.avax.network/dexalot","api":""},"432204":{"name":"Dexalot Subnet","explorer":"https://subnets.avax.network/dexalot","api":""},"513100":{"name":"ethereum Fair","explorer":"https://www.oklink.com/ethf","api":""},"534351":{"name":"Scroll Sepolia Testnet","explorer":"https://sepolia.scrollscan.dev","api":""},"534352":{"name":"Scroll","explorer":"https://scrollscan.com","api":""},"534353":{"name":"Scroll Alpha Testnet","explorer":"https://alpha-blockscout.scroll.io","api":""},"534849":{"name":"Shinarium Beta","explorer":"https://shinascan.shinarium.org","api":""},"535037":{"name":"BeanEco SmartChain","explorer":"https://Bescscan.io","api":""},"622277":{"name":"Rethereum Mainnet","explorer":"https://explorer.rethereum.org","api":""},"641230":{"name":"Bear Network Chain Mainnet","explorer":"https://brnkscan.bearnetwork.net","api":""},"651940":{"name":"ALL Mainnet","explorer":"https://alltra.global","api":""},"666888":{"name":"Hela Official Runtime Testnet","explorer":"https://testnet-blockexplorer.helachain.com","api":""},"751230":{"name":"Bear Network Chain Testnet","explorer":"https://brnktest-scan.bearnetwork.net","api":""},"761412":{"name":"Miexs Smartchain","explorer":"https://miexs.com","api":""},"800001":{"name":"OctaSpace","explorer":"https://explorer.octa.space","api":""},"827431":{"name":"CURVE Mainnet","explorer":"https://curvescan.io","api":""},"888888":{"name":"Vision - Mainnet","explorer":"https://www.visionscan.org","api":""},"900000":{"name":"Posichain Mainnet Shard 0","explorer":"https://explorer.posichain.org","api":""},"910000":{"name":"Posichain Testnet Shard 0","explorer":"https://explorer-testnet.posichain.org","api":""},"920000":{"name":"Posichain Devnet Shard 0","explorer":"https://explorer-devnet.posichain.org","api":""},"920001":{"name":"Posichain Devnet Shard 1","explorer":"https://explorer-devnet.posichain.org","api":""},"923018":{"name":"FNCY Testnet","explorer":"https://fncyscan-testnet.fncy.world","api":""},"955305":{"name":"Eluvio Content Fabric","explorer":"https://explorer.eluv.io","api":""},"988207":{"name":"Ecrox Chain Mainnet","explorer":"https://ecroxscan.com","api":""},"1261120":{"name":"zKatana","explorer":"https://zkatana.blockscout.com","api":""},"1337702":{"name":"Kintsugi","explorer":"https://explorer.kintsugi.themerge.dev","api":""},"1337802":{"name":"Kiln","explorer":"https://explorer.kiln.themerge.dev","api":""},"1337803":{"name":"Zhejiang","explorer":"https://zhejiang.beaconcha.in","api":""},"2021398":{"name":"DeBank Testnet","explorer":"https://explorer.testnet.debank.com","api":""},"2099156":{"name":"Plian Mainnet Main","explorer":"https://piscan.plian.org/pchain","api":""},"3441005":{"name":"Manta Pacific Testnet","explorer":"https://manta-testnet.calderaexplorer.xyz","api":""},"4000003":{"name":"AltLayer Zero Gas Network","explorer":"https://zero-explorer.alt.technology","api":""},"5167003":{"name":"MXC Wannsee zkEVM Testnet","explorer":"https://wannsee-explorer.mxc.com","api":""},"5201420":{"name":"Electroneum Testnet","explorer":"https://blockexplorer.thesecurityteam.rocks","api":""},"5555555":{"name":"Imversed Mainnet","explorer":"https://txe.imversed.network","api":""},"5555558":{"name":"Imversed Testnet","explorer":"https://txe-test.imversed.network","api":""},"7225878":{"name":"Saakuru Mainnet","explorer":"https://explorer.saakuru.network","api":""},"7668378":{"name":"QL1 Testnet","explorer":"https://testnet.qom.one","api":""},"7777777":{"name":"Zora","explorer":"https://explorer.zora.energy","api":""},"8007736":{"name":"Plian Mainnet Subchain 1","explorer":"https://piscan.plian.org/child_0","api":""},"9322252":{"name":"XCAP","explorer":"https://xcap-mainnet.explorer.xcap.network","api":""},"9322253":{"name":"Milvine","explorer":"https://xcap-milvine.explorer.xcap.network","api":""},"10067275":{"name":"Plian Testnet Subchain 1","explorer":"https://testnet.plian.org/child_test","api":""},"10101010":{"name":"Soverun Mainnet","explorer":"https://explorer.soverun.com","api":""},"11155111":{"name":"Sepolia","explorer":"https://sepolia.etherscan.io","api":""},"16658437":{"name":"Plian Testnet Main","explorer":"https://testnet.plian.org/testnet","api":""},"20181205":{"name":"quarkblockchain","explorer":"https://qkiscan.io","api":""},"20201022":{"name":"Pego Network","explorer":"https://scan.pego.network","api":""},"22052002":{"name":"Excelon Mainnet","explorer":"https://explorer.excelon.io","api":""},"27082017":{"name":"Excoincial Chain Volta-Testnet","explorer":"https://testnet-explorer.exlscan.com","api":""},"27082022":{"name":"Excoincial Chain Mainnet","explorer":"https://exlscan.com","api":""},"29032022":{"name":"Flachain Mainnet","explorer":"https://explorer.flaexchange.top","api":""},"65010000":{"name":"Autonity Bakerloo (Thames) Testnet","explorer":"https://bakerloo.autonity.org","api":""},"65100000":{"name":"Autonity Piccadilly (Thames) Testnet","explorer":"https://piccadilly.autonity.org","api":""},"68840142":{"name":"Frame Testnet","explorer":"https://explorer.testnet.frame.xyz","api":""},"88888888":{"name":"T.E.A.M Blockchain","explorer":"https://teamblockchain.team","api":""},"222000222":{"name":"Kanazawa","explorer":"https://subnets-test.avax.network/meld","api":""},"245022926":{"name":"Neon EVM DevNet","explorer":"https://devnet.explorer.neon-labs.org","api":""},"245022934":{"name":"Neon EVM MainNet","explorer":"https://neonscan.org","api":""},"245022940":{"name":"Neon EVM TestNet","explorer":"https://testnet.explorer.neon-labs.org","api":""},"278611351":{"name":"Razor Skale Chain","explorer":"https://turbulent-unique-scheat.explorer.mainnet.skalenodes.com","api":""},"311752642":{"name":"OneLedger Mainnet","explorer":"https://mainnet-explorer.oneledger.network","api":""},"333000333":{"name":"Meld","explorer":"https://subnets.avax.network/meld","api":""},"344106930":{"name":"Calypso NFT Hub (SKALE Testnet)","explorer":"https://staging-utter-unripe-menkar.explorer.staging-v3.skalenodes.com","api":""},"503129905":{"name":"Nebula Staging","explorer":"https://staging-faint-slimy-achird.explorer.staging-v3.skalenodes.com","api":""},"999999999":{"name":"Zora Sepolia Testnet","explorer":"https://sepolia.explorer.zora.energy","api":""},"1273227453":{"name":"HUMAN Protocol","explorer":"https://wan-red-ain.explorer.mainnet.skalenodes.com","api":""},"1313161554":{"name":"Aurora Mainnet","explorer":"https://aurorascan.dev","api":""},"1313161555":{"name":"Aurora Testnet","explorer":"https://testnet.aurorascan.dev","api":""},"1351057110":{"name":"Chaos (SKALE Testnet)","explorer":"https://staging-fast-active-bellatrix.explorer.staging-v3.skalenodes.com","api":""},"1380996178":{"name":"RaptorChain","explorer":"https://explorer.raptorchain.io","api":""},"1482601649":{"name":"Nebula Mainnet","explorer":"https://green-giddy-denebola.explorer.mainnet.skalenodes.com","api":""},"1564830818":{"name":"Calypso NFT Hub (SKALE)","explorer":"https://honorable-steel-rasalhague.explorer.mainnet.skalenodes.com","api":""},"1666600000":{"name":"Harmony Mainnet Shard 0","explorer":"https://explorer.harmony.one","api":""},"1666700000":{"name":"Harmony Testnet Shard 0","explorer":"https://explorer.testnet.harmony.one","api":""},"2046399126":{"name":"Europa SKALE Chain","explorer":"https://elated-tan-skat.explorer.mainnet.skalenodes.com","api":""},"2863311531":{"name":"Ancient8 Testnet","explorer":"https://testnet.a8scan.io","api":""},"4216137055":{"name":"OneLedger Testnet Frankenstein","explorer":"https://frankenstein-explorer.oneledger.network","api":""},"11297108099":{"name":"Palm Testnet","explorer":"https://explorer.palm-uat.xyz","api":""},"11297108109":{"name":"Palm","explorer":"https://explorer.palm.io","api":""},"111222333444":{"name":"Alphabet Mainnet","explorer":"https://scan.alphabetnetwork.org","api":""},"197710212030":{"name":"Ntity Mainnet","explorer":"https://blockscout.ntity.io","api":""},"197710212031":{"name":"Haradev Testnet","explorer":"https://blockscout.haradev.com","api":""},"383414847825":{"name":"Zeniq","explorer":"https://smart.zeniq.net","api":""},"666301171999":{"name":"PDC Mainnet","explorer":"https://scan.ipdc.io","api":""}}